sprint2/MUX_SOMADOR_REGISTRADOR/design.sv
// Code your design here
// Code your design here
module mux2x1 (
  input logic [3:0]i0,
  input logic [3:0]i1,
  output logic [3:0] out,
  input logic sel
);
  
  always @*
    if (sel)
      out = i1;
  
  	else
    out =i0;
  
endmodule

// Code your design here
module somador( input [3:0] a,b, output [3:0] res);
  
  assign res = a + b;
  
endmodule

// Code your design here
module registrador(
  			input logic clk, 
  			input logic reset,
  			input logic enable,
  			input logic [3:0] in, 
  			output reg [3:0] out
);
  
  always @(posedge clk or negedge reset)
    begin
   
      if(!reset)
        out <= 0;
    else if (enable) 
        out <= in;
      else
        out <= out;
          
  end
endmodule

//mux, somador e Registrador de 4bits
module muxSomadorRegistrador (
  input  logic [3:0] A,
  input  logic [3:0] B,
  input  logic [3:0] C,
  input  logic S,
  input logic CLK,
  input logic RESET,
  input logic ENABLE,
  output logic [3:0] RES
  
);
  wire logic [3:0] somador_out;
  wire logic [3:0] mux_out;

  // Instanciação do MUX
  mux2x1 u_mux (.i0(B), .i1(C), .sel(S), .out(mux_out));

  // Instanciação do somador
  somador u_somador (.a(A),.b(mux_out),.res(somador_out));
  
  //instanciação do registrador
  registrador u_registrador (.in(somador_out),.clk(CLK), .reset(RESET), .enable(ENABLE), .out(RES));
  


endmodule

sprint2/MUX_SOMADOR_REGISTRADOR/testbench.sv
// Code your testbench here
// or browse Examples

module muxSomadorRegistrador_t;
   //sinais
  logic [3:0] A;
  logic [3:0] B;
  logic [3:0] C;
  logic S;
  logic CLK;
  logic RESET;
  logic ENABLE;
  logic [3:0] RES;
  
  // Instância do módulo
  muxSomadorRegistrador inst1(A,B,C,S,CLK, RESET,ENABLE, RES);
  
  always #5 CLK = ~CLK;
  
  initial begin
    CLK = 0; // Inicializa o clock para evitar 'X'
    S = 1;
    RESET = 1; // Deassert reset
    ENABLE = 1; // Começa com enable ativo para registrar dados
    S = 1;
    A = 4'b0000;
    B = 4'b0001;
	C = 4'b0101;
    #10; // Deixa o sistema estabilizar um pouco, talvez um ou dois ciclos

    RESET = 0; // Ativa o reset (borda de descida) para zerar o registrador
    #5;       // Mantém o reset por um tempo
    RESET = 1; // Desativa o reset

    #5; // Espera um pouco, talvez até a próxima borda de clock

    // Teste de registro com enable = 1
    ENABLE = 1;
    A = 4'b1010; // Este dado deve ser registrado no próximo posedge clk
    #10;          // Aguarda um ciclo completo (dado já deveria ter sido registrado)

    A = 4'b0001; // Este dado deve ser registrado no próximo posedge clk
    #10;

    // Teste de retenção com enable = 0
    S= 0;
    ENABLE = 0;
    A = 4'b0010; // Este dado NÃO deve ser registrado, o valor anterior (0001) deve ser mantido
    #10;
; // Este dado TAMBÉM NÃO deve ser registrado

    // Ativa o enable novamente para registrar o último valor de In_data (0101)
    ENABLE = 1;
    #10; // Agora 0101 deve ser registrado

    #25 $finish; // Termina a simulação
end
  
  initial begin
     $dumpfile("test.vcd");
    $dumpvars(0, inst1);
   end
  
endmodule

sprint2/MUX_SOMADOR_REGISTRADOR/test.vcd
$date
    Jun 25, 2025  17:23:01
$end
$version
    TOOL:	xmsim	23.09-s001
$end
$timescale
    1 ns
$end

$scope module muxSomadorRegistrador_t $end

$scope module inst1 $end
$var wire      4 !    A [3:0] $end
$var wire      4 "    B [3:0] $end
$var wire      4 #    C [3:0] $end
$var wire      1 $    S  $end
$var wire      1 %    CLK  $end
$var wire      1 &    RESET  $end
$var wire      1 '    ENABLE  $end
$var reg       4 (    RES [3:0] $end
$var wire      4 )    somador_out [3:0] $end
$var wire      4 *    mux_out [3:0] $end

$scope module u_mux $end
$var wire      4 "    i0 [3:0] $end
$var wire      4 #    i1 [3:0] $end
$var reg       4 +    out [3:0] $end
$var wire      1 $    sel  $end
$upscope $end


$scope module u_somador $end
$var wire      4 !    a [3:0] $end
$var wire      4 *    b [3:0] $end
$var wire      4 )    res [3:0] $end
$upscope $end


$scope module u_registrador $end
$var wire      1 %    clk  $end
$var wire      1 &    reset  $end
$var wire      1 '    enable  $end
$var wire      4 )    in [3:0] $end
$var reg       4 ,    out [3:0] $end
$upscope $end

$upscope $end

$upscope $end

$enddefinitions $end
$dumpvars
b0 !
b1 "
b101 #
1$
0%
1&
1'
bx (
b101 )
b101 *
b101 +
bx ,
$end
#5
1%
b101 ,
b101 (
#10
0%
0&
b0 ,
b0 (
#15
1%
1&
b101 ,
b101 (
#20
0%
b1010 !
b1111 )
#25
1%
b1111 ,
b1111 (
#30
0%
b1 !
b110 )
#35
1%
b110 ,
b110 (
#40
0%
b10 !
0'
0$
b1 +
b1 *
b111 )
b11 )
#45
1%
#50
0%
1'
#55
1%
b11 ,
b11 (
