sprint2/desafio_sprint2/design.sv
// Code your design here
module mux2x1 (
  input logic [3:0]i0,
  input logic [3:0]i1,
  output logic [3:0] out,
  input logic sel
);
  
  always @*
    if (sel)
      out = i0;
  
  	else
    out =i1;
  
endmodule

// Code your design here
module somador( input [3:0] a,b, output [3:0] res);
  
  assign res = a + b;
  
endmodule

// Code your design here
module registrador(
  			input logic clk, 
  			input logic reset,
  			input logic enable,
  			input logic [3:0] in, 
  			output reg [3:0] out
);
  
  always @(posedge clk or negedge reset)
    begin
   
      if(!reset)
        out <= 0;
    else if (enable) 
        out <= in;
      else
        out <= out;
          
  end
endmodule

module contador16(
    input logic clk,             
    input logic reset,           
    input logic dir_cont,  // Sinal de direção: 0 para crescente (0-F), 1 para decrescente (F-0
  	input logic enable_contador, 
    output logic [3:0] contagem_out // Saída de 4 bits que mostra o valor da contagem
);
  
	logic [3:0] current_count;     // saída do registrador
    logic [3:0] next_count_val;    // saída do somador
    logic [3:0] mux_input_val;     // Valor que o mux seleciona para somar/subtrair (+1 ou -1)
  
  localparam [3:0] INCREMENTO = 4'b0001; // Valor para somar na contagem crescente
  localparam [3:0] DECREMENTO = 4'b1111; // Valor para somar na contagem decrescente (equivale a -1)
  
  //instancia do registrador
  
  registrador u_registrador( .clk(clk), .enable(enable_contador), .reset(reset),.in(next_count_val), .out(current_count));
  
  //instancia do mux
  
  mux2x1 u_mux2x1( .i1(INCREMENTO), .i0(DECREMENTO), .sel(dir_cont), .out(mux_input_val));
  
  //instancia do somador
  somador u_somador(.a(current_count), .b(mux_input_val), .res(next_count_val));
  
  assign contagem_out = current_count;
  
endmodule

sprint2/desafio_sprint2/testbench.sv
// Code your testbench here
// or browse Examples
module contador16_t;
  
  //sinais
  
  logic clk;
  logic reset;
  logic dir_cont;
  logic [3:0] contagem_out;
  logic enable_contador;
  // instanciação
  
  contador16 inst1( clk, reset, dir_cont,enable_contador, contagem_out );
  
  always #5 clk = ~clk;
  
  initial
    begin
     // 1. Inicialização dos sinais no tempo 0 para evitar valores 'X' (indefinidos)
        clk = 0;
        reset = 1;// Reset inicialmente desativado (nível alto)
        enable_contador = 0; // Contador inicialmente desabilitado
        dir_cont = 0;      // Direção inicial: Crescente

        // 3. Sequência de Teste

        $display("Tempo %0t: Inicio da simulacao do Contador.", $time);
        #10; // Pequeno atraso inicial para estabilização

        // --- Cenario 1: Teste de Reset Assincrono ---
        $display("Tempo %0t: --- Teste de Reset Assincrono ---", $time);
        reset = 0; // Ativa o reset (vai zerar a contagem imediatamente)
        #10;       // Mantém o reset ativo por 10ns
        reset = 1; // Desativa o reset

        // --- Cenario 2: Contagem Crescente (0-F) ---
        enable_contador = 1; // Habilita o contador
        dir_cont = 0;        // Define a direção como crescente
        $display("Tempo %0t: --- Teste de Contagem Crescente (0-F) ---", $time);
        $display("Tempo %0t: Habilitando contador crescente. Valor inicial: %h", $time, contagem_out);

        // Contar por mais de 16 ciclos para verificar o wrap-around (0->F->0->1...)
        for (int i = 0; i < 20; i++) begin
            #10; // Aguarda um ciclo de clock completo
            $display("Tempo %0t: Contagem = %h (Esperado: %h)", $time, contagem_out, (i < 16 ? i : (i - 16)));
        end
        $display("Tempo %0t: Fim do teste de contagem crescente.", $time);


         //ario 3: Teste de Desabilitar Contador (Enable = 0) ---
        enable_contador = 0; // Desabilita o contador
        $display("Tempo %0t: --- Teste de Desabilitar Contador (Enable = 0) ---", $time);
        $display("Tempo %0t: Desabilitando contador. Contagem deve manter %h.", $time, contagem_out);
        #30; // Aguarda 3 ciclos. A contagem NÃO deve mudar.
        $display("Tempo %0t: Fim do teste de desabilitar contador.", $time);


        // --- Cenario 4: Contagem Decrescente (F-0) ---
        // Primeiro, forçamos um reset para 0, para termos um ponto de partida conhecido.
        $display("Tempo %0t: --- Teste de Contagem Decrescente (F-0) ---", $time);
        $display("Tempo %0t: Aplicando Reset para 0 antes da contagem decrescente.", $time);
        reset = 0; // Reset para 0
        #10;
        reset = 1;

        enable_contador = 1; // Habilita o contador
        dir_cont = 1;        // Define a direção como decrescente
        $display("Tempo %0t: Habilitando contador decrescente. Valor inicial: %h", $time, contagem_out);

        // Contar por mais de 16 ciclos para verificar o wrap-around (0->F->E...)
        for (int i = 0; i < 20; i++) begin
            #10; // Aguarda um ciclo de clock completo
            $display("Tempo %0t: Contagem = %h", $time, contagem_out);
        end
        $display("Tempo %0t: Fim do teste de contagem decrescente.", $time);

        // --- Finalização da Simulação ---
        $display("Tempo %0t: Fim da simulacao do Contador.", $time);
        #20; // Pequeno atraso final antes de terminar a simulação
        $finish; // Termina a simulação
    end
    
  
  initial begin
     $dumpfile("test.vcd");
    $dumpvars(0, inst1);
   end
  
  
endmodule

sprint2/desafio_sprint2/test.vcd
$date
    Jun 25, 2025  17:20:41
$end
$version
    TOOL:	xmsim	23.09-s001
$end
$timescale
    1 ns
$end

$scope module contador16_t $end

$scope module inst1 $end
$var wire      1 !    clk  $end
$var wire      1 "    reset  $end
$var wire      1 #    dir_cont  $end
$var wire      1 $    enable_contador  $end
$var reg       4 %    contagem_out [3:0] $end
$var reg       4 &    current_count [3:0] $end
$var reg       4 '    next_count_val [3:0] $end
$var reg       4 (    mux_input_val [3:0] $end
$var parameter  4 )    INCREMENTO [3:0] $end
$var parameter  4 *    DECREMENTO [3:0] $end

$scope module u_registrador $end
$var wire      1 !    clk  $end
$var wire      1 "    reset  $end
$var wire      1 $    enable  $end
$var wire      4 +    in [3:0] $end
$var reg       4 ,    out [3:0] $end
$upscope $end


$scope module u_mux2x1 $end
$var wire      4 -    i0 [3:0] $end
$var wire      4 .    i1 [3:0] $end
$var reg       4 /    out [3:0] $end
$var wire      1 #    sel  $end
$upscope $end


$scope module u_somador $end
$var wire      4 0    a [3:0] $end
$var wire      4 1    b [3:0] $end
$var wire      4 2    res [3:0] $end
$upscope $end

$upscope $end

$upscope $end

$enddefinitions $end
$dumpvars
b1111 *
b1 )
0!
1"
0#
0$
bx %
bx &
bx '
b1 (
bx +
bx ,
b1111 -
b1 .
b1 /
bx 0
b1 1
bx 2
$end
#5
1!
#10
0!
0"
b0 ,
b0 &
b0 %
b0 0
b1 2
b1 '
b1 +
#15
1!
#20
0!
1$
1"
#25
1!
b1 ,
b1 &
b1 %
b1 0
b10 2
b10 '
b10 +
#30
0!
#35
1!
b10 ,
b10 &
b10 %
b10 0
b11 2
b11 '
b11 +
#40
0!
#45
1!
b11 ,
b11 &
b11 %
b11 0
b100 2
b100 '
b100 +
#50
0!
#55
1!
b100 ,
b100 &
b100 %
b100 0
b101 2
b101 '
b101 +
#60
0!
#65
1!
b101 ,
b101 &
b101 %
b101 0
b110 2
b110 '
b110 +
#70
0!
#75
1!
b110 ,
b110 &
b110 %
b110 0
b111 2
b111 '
b111 +
#80
0!
#85
1!
b111 ,
b111 &
b111 %
b111 0
b1000 2
b1000 '
b1000 +
#90
0!
#95
1!
b1000 ,
b1000 &
b1000 %
b1000 0
b1001 2
b1001 '
b1001 +
#100
0!
#105
1!
b1001 ,
b1001 &
b1001 %
b1001 0
b1010 2
b1010 '
b1010 +
#110
0!
#115
1!
b1010 ,
b1010 &
b1010 %
b1010 0
b1011 2
b1011 '
b1011 +
#120
0!
#125
1!
b1011 ,
b1011 &
b1011 %
b1011 0
b1100 2
b1100 '
b1100 +
#130
0!
#135
1!
b1100 ,
b1100 &
b1100 %
b1100 0
b1101 2
b1101 '
b1101 +
#140
0!
#145
1!
b1101 ,
b1101 &
b1101 %
b1101 0
b1110 2
b1110 '
b1110 +
#150
0!
#155
1!
b1110 ,
b1110 &
b1110 %
b1110 0
b1111 2
b1111 '
b1111 +
#160
0!
#165
1!
b1111 ,
b1111 &
b1111 %
b1111 0
b0 2
b0 '
b0 +
#170
0!
#175
1!
b0 ,
b0 &
b0 %
b0 0
b1 2
b1 '
b1 +
#180
0!
#185
1!
b1 ,
b1 &
b1 %
b1 0
b10 2
b10 '
b10 +
#190
0!
#195
1!
b10 ,
b10 &
b10 %
b10 0
b11 2
b11 '
b11 +
#200
0!
#205
1!
b11 ,
b11 &
b11 %
b11 0
b100 2
b100 '
b100 +
#210
0!
#215
1!
b100 ,
b100 &
b100 %
b100 0
b101 2
b101 '
b101 +
#220
0!
0$
#225
1!
#230
0!
#235
1!
#240
0!
#245
1!
#250
0!
0"
b0 ,
b0 &
b0 %
b0 0
b1 2
b1 '
b1 +
#255
1!
#260
0!
1#
1$
1"
b1111 /
b1111 (
b1111 1
b1111 2
b1111 '
b1111 +
#265
1!
b1111 ,
b1111 &
b1111 %
b1111 0
b1110 2
b1110 '
b1110 +
#270
0!
#275
1!
b1110 ,
b1110 &
b1110 %
b1110 0
b1101 2
b1101 '
b1101 +
#280
0!
#285
1!
b1101 ,
b1101 &
b1101 %
b1101 0
b1100 2
b1100 '
b1100 +
#290
0!
#295
1!
b1100 ,
b1100 &
b1100 %
b1100 0
b1011 2
b1011 '
b1011 +
#300
0!
#305
1!
b1011 ,
b1011 &
b1011 %
b1011 0
b1010 2
b1010 '
b1010 +
#310
0!
#315
1!
b1010 ,
b1010 &
b1010 %
b1010 0
b1001 2
b1001 '
b1001 +
#320
0!
#325
1!
b1001 ,
b1001 &
b1001 %
b1001 0
b1000 2
b1000 '
b1000 +
#330
0!
#335
1!
b1000 ,
b1000 &
b1000 %
b1000 0
b111 2
b111 '
b111 +
#340
0!
#345
1!
b111 ,
b111 &
b111 %
b111 0
b110 2
b110 '
b110 +
#350
0!
#355
1!
b110 ,
b110 &
b110 %
b110 0
b101 2
b101 '
b101 +
#360
0!
#365
1!
b101 ,
b101 &
b101 %
b101 0
b100 2
b100 '
b100 +
#370
0!
#375
1!
b100 ,
b100 &
b100 %
b100 0
b11 2
b11 '
b11 +
#380
0!
#385
1!
b11 ,
b11 &
b11 %
b11 0
b10 2
b10 '
b10 +
#390
0!
#395
1!
b10 ,
b10 &
b10 %
b10 0
b1 2
b1 '
b1 +
#400
0!
#405
1!
b1 ,
b1 &
b1 %
b1 0
b0 2
b0 '
b0 +
#410
0!
#415
1!
b0 ,
b0 &
b0 %
b0 0
b1111 2
b1111 '
b1111 +
#420
0!
#425
1!
b1111 ,
b1111 &
b1111 %
b1111 0
b1110 2
b1110 '
b1110 +
#430
0!
#435
1!
b1110 ,
b1110 &
b1110 %
b1110 0
b1101 2
b1101 '
b1101 +
#440
0!
#445
1!
b1101 ,
b1101 &
b1101 %
b1101 0
b1100 2
b1100 '
b1100 +
#450
0!
#455
1!
b1100 ,
b1100 &
b1100 %
b1100 0
b1011 2
b1011 '
b1011 +
#460
0!
#465
1!
b1011 ,
b1011 &
b1011 %
b1011 0
b1010 2
b1010 '
b1010 +
#470
0!
#475
1!
b1010 ,
b1010 &
b1010 %
b1010 0
b1001 2
b1001 '
b1001 +
