sprint2/Registrador/design.sv
// Code your design here

module registrador(
  			input logic clk, 
  			input logic reset,
  			input logic enable,
  			input logic [3:0] in, 
  			output reg [3:0] out
);
  reg [3:0] valor_armazenado;
  
  always @(posedge clk or negedge reset)
    begin
   
      if(!reset)
        out <= 0;
    else if (clk)
        if (enable) 
        valor_armazenado <= in;
      else
        out = valor_armazenado;
          
  end
  
   
    
endmodule

sprint2/Registrador/testbench.sv
// Code your testbench here
// or browse Examples

module resgistrador_t;
  
 	//sinais 
	logic clk;
	logic reset;
  	logic enable;
  	logic [3:0]in;
  	reg [3:0]out;

// Instância do módulo
  registrador inst1( clk, reset,enable, in, out);
  
  always #5 clk = ~clk;
  
  initial begin
    clk = 0; // Inicializa o clock para evitar 'X'
    reset = 1; // Deassert reset
    enable = 1; // Começa com enable ativo para registrar dados
    in = 4'b0000;

    #10; // Deixa o sistema estabilizar um pouco, talvez um ou dois ciclos

    reset = 0; // Ativa o reset (borda de descida) para zerar o registrador
    #5;       // Mantém o reset por um tempo
    reset = 1; // Desativa o reset

    #5; // Espera um pouco, talvez até a próxima borda de clock

    // Teste de registro com enable = 1
    enable = 1;
    in = 4'b1010; // Este dado deve ser registrado no próximo posedge clk
    #10;          // Aguarda um ciclo completo (dado já deveria ter sido registrado)

    in = 4'b0001; // Este dado deve ser registrado no próximo posedge clk
    #10;

    // Teste de retenção com enable = 0
    enable = 0;
    in = 4'b1111; // Este dado NÃO deve ser registrado, o valor anterior (0001) deve ser mantido
    #10;

    in = 4'b0101; // Este dado TAMBÉM NÃO deve ser registrado
    #10;

    // Ativa o enable novamente para registrar o último valor de In_data (0101)
    enable = 1;
    #10; // Agora 0101 deve ser registrado

    #25 $finish; // Termina a simulação
end
  
  initial begin
     $dumpfile("test.vcd");
    $dumpvars(0, inst1);
   end
  
endmodule

sprint2/Registrador/test.vcd
$date
    Jun 25, 2025  17:25:34
$end
$version
    TOOL:	xmsim	23.09-s001
$end
$timescale
    1 ns
$end

$scope module resgistrador_t $end

$scope module inst1 $end
$var wire      1 !    clk  $end
$var wire      1 "    reset  $end
$var wire      1 #    enable  $end
$var wire      4 $    in [3:0] $end
$var reg       4 %    out [3:0] $end
$var reg       4 &    valor_armazenado [3:0] $end
$upscope $end

$upscope $end

$enddefinitions $end
$dumpvars
0!
1"
1#
b0 $
bx %
bx &
$end
#5
1!
b0 &
#10
0!
0"
b0 %
#15
1!
1"
#20
0!
b1010 $
#25
1!
b1010 &
#30
0!
b1 $
#35
1!
b1 &
#40
0!
b1111 $
0#
#45
1!
b1 %
#50
0!
b101 $
#55
1!
#60
0!
1#
#65
1!
b101 &
